feincms_oembed/__init__.py
feincms_oembed/admin.py
feincms_oembed/contents.py
feincms_oembed/models.py
feincms_oembed/providers.py
feincms_oembed/migrations/0001_initial.py
feincms_oembed/migrations/__init__.py
feincms_oembed-2.0.0.dist-info/LICENSE
feincms_oembed-2.0.0.dist-info/METADATA
feincms_oembed-2.0.0.dist-info/WHEEL
feincms_oembed-2.0.0.dist-info/top_level.txt
feincms_oembed-2.0.0.dist-info/RECORD
